setup.py
ecdsa_recover/ecdsa_recover.pyx
ecdsa_recover.egg-info/PKG-INFO
ecdsa_recover.egg-info/SOURCES.txt
ecdsa_recover.egg-info/dependency_links.txt
ecdsa_recover.egg-info/requires.txt
ecdsa_recover.egg-info/top_level.txt