Metadata-Version: 1.1
Name: ecdsa-recover
Version: 0.1.6
Summary: faster implementation of ecdsa recover using cython + gmp
Home-page: https://github.com/heikoheiko/cy_ecdsa_recover
Author: HeikoHeiko
Author-email: heiko@ethdev.com
License: BSD
Keywords: ecdsa recover ethereum cython gmp
Platform: UNKNOWN
Classifier: Development Status :: 2 - Pre-Alpha
Classifier: Intended Audience :: Developers
Classifier: License :: OSI Approved :: BSD License
Classifier: Natural Language :: English
Classifier: Programming Language :: Python :: 2
Classifier: Programming Language :: Python :: 2.7
